conda_souschef-3.0.1.dist-info/licenses/AUTHORS
conda_souschef-3.0.1.dist-info/licenses/LICENSE
souschef/__init__.py
souschef/_version.py
souschef/comment.py
souschef/config.py
souschef/ingredient.py
souschef/jinja_expression.py
souschef/mixins.py
souschef/recipe.py
souschef/section.py
souschef/tools.py
conda_souschef-3.0.1.dist-info/METADATA
conda_souschef-3.0.1.dist-info/WHEEL
conda_souschef-3.0.1.dist-info/top_level.txt
conda_souschef-3.0.1.dist-info/RECORD
