Metadata-Version: 2.4
Name: conda-souschef
Version: 3.0.1
Summary: Project to handle conda recipes
Home-page: https://github.com/marcelotrevisani/souschef
Author: Marcelo Duarte Trevisani
Author-email: marceloduartetrevisani@gmail.com
License: Apache-2.0
Project-URL: Source, https://github.com/marcelotrevisani/souschef
Requires-Python: >=3.8
License-File: LICENSE
License-File: AUTHORS
Requires-Dist: ruamel.yaml>=0.15.3
Requires-Dist: ruamel.yaml.jinja2
Provides-Extra: testing
Requires-Dist: pytest; extra == "testing"
Requires-Dist: mock; extra == "testing"
Requires-Dist: pytest-cov; extra == "testing"
Dynamic: author
Dynamic: author-email
Dynamic: description
Dynamic: description-content-type
Dynamic: home-page
Dynamic: license
Dynamic: license-file
Dynamic: project-url
Dynamic: provides-extra
Dynamic: requires-dist
Dynamic: requires-python
Dynamic: summary
